pyladoc/__init__.py
pyladoc/latex.py
pyladoc/latex_escaping.py
pyladoc/py.typed
pyladoc/svg_tools.py
pyladoc/templates/default_template.tex
pyladoc/templates/test_template.html
pyladoc-1.2.4.dist-info/licenses/LICENSE
pyladoc-1.2.4.dist-info/METADATA
pyladoc-1.2.4.dist-info/WHEEL
pyladoc-1.2.4.dist-info/top_level.txt
pyladoc-1.2.4.dist-info/RECORD
