Metadata-Version: 2.4
Name: pyladoc
Version: 1.2.4
Summary: Package for generating HTML and PDF/latex from python code
Author-email: Nicolas Kruse <nicolas.kruse@nonan.net>
License-Expression: MIT
Project-URL: Homepage, https://github.com/Nonannet/pyladoc
Project-URL: Repository, https://github.com/Nonannet/pyladoc
Project-URL: Issues, https://github.com/Nonannet/pyladoc/issues
Project-URL: documentation, https://nonannet.github.io/pyladoc/
Classifier: Programming Language :: Python :: 3
Classifier: Operating System :: OS Independent
Requires-Python: >=3.10
License-File: LICENSE
Requires-Dist: markdown>=3.3.0
Provides-Extra: dev
Requires-Dist: pytest; extra == "dev"
Requires-Dist: flake8; extra == "dev"
Requires-Dist: mypy; extra == "dev"
Requires-Dist: lxml; extra == "dev"
Requires-Dist: types-lxml; extra == "dev"
Requires-Dist: types-Markdown; extra == "dev"
Requires-Dist: pandas-stubs; extra == "dev"
Requires-Dist: requests; extra == "dev"
Requires-Dist: matplotlib>=3.1.1; extra == "dev"
Requires-Dist: pandas>=2.0.0; extra == "dev"
Requires-Dist: Jinja2; extra == "dev"
Provides-Extra: doc-build
Requires-Dist: sphinx; extra == "doc-build"
Requires-Dist: pydata_sphinx_theme; extra == "doc-build"
Requires-Dist: sphinx-autodoc-typehints; extra == "doc-build"
Requires-Dist: myst-parser; extra == "doc-build"
Dynamic: license-file
